pabulib/__init__.py
pabulib/checker.py
pabulib_helpers/__init__.py
pabulib_helpers/fields.py
pabulib_helpers/fields_validations.py
pabulib_helpers/load_pb_file.py
pabulib_helpers/utilities.py
pabulib_checker-0.3.2.dist-info/METADATA
pabulib_checker-0.3.2.dist-info/WHEEL
pabulib_checker-0.3.2.dist-info/top_level.txt
pabulib_checker-0.3.2.dist-info/RECORD
