Metadata-Version: 2.4
Name: pabulib-checker
Version: 0.3.2
Summary: A Python library for validating files in the PB (Pabulib) format, ensuring compliance with the standards described at pabulib.org/format.
Author-email: Ignacy Janiszewski <ignacy.janiszewsk@uj.edu.pl>
License-Expression: MIT
Project-URL: Homepage, https://github.com/pabulib/checker
Project-URL: Repository, https://github.com/pabulib/checker
Project-URL: Issues, https://github.com/pabulib/checker/issues
Keywords: checker,file validation,python,pabulib
Classifier: Programming Language :: Python :: 3
Classifier: Operating System :: OS Independent
Requires-Python: >=3.7
Requires-Dist: pycountry>=24.6.1
